simplicits/__init__.py
simplicits/simplicits.py
simplicits/simplicits_viewer.py
simplicits/utils.py
simplicits/trainer/__init__.py
simplicits/trainer/loss.py
simplicits/trainer/model.py
simplicits/trainer/optimizer.py
simplicits/trainer/scheduler.py
simplicits/trainer/train.py
simplicits/viewer_utils/__init__.py
simplicits/viewer_utils/playback_panel.py
simplicits/viewer_utils/render_panel.py
simplicits/viewer_utils/utils.py
simplicits/viewer_utils/viewer.py
simplicits-0.1.0.dist-info/METADATA
simplicits-0.1.0.dist-info/WHEEL
simplicits-0.1.0.dist-info/entry_points.txt
simplicits-0.1.0.dist-info/top_level.txt
simplicits-0.1.0.dist-info/RECORD
