Metadata-Version: 2.1
Name: simplicits
Version: 0.1.0
Summary: unofficial implementation of simplicits in nerfstudio.
License: Apache 2.0
Project-URL: Homepage, https://github.com/Rishit-dagli/
Requires-Python: >=3.8.0
Requires-Dist: nerfstudio>=1.1.5
Requires-Dist: torch
Requires-Dist: torchvision
Requires-Dist: numpy
Requires-Dist: trimesh
Requires-Dist: accelerate
Requires-Dist: safetensors
Requires-Dist: einops
Requires-Dist: kaolin
